CHANGELOG.txt
LICENSE.txt
MANIFEST.in
README.txt
setup.cfg
setup.py
test.py
rltexe.egg-info/PKG-INFO
rltexe.egg-info/SOURCES.txt
rltexe.egg-info/dependency_links.txt
rltexe.egg-info/top_level.txt
wteam.egg-info/SOURCES.txt
wteam.egg-info/dependency_links.txt
wteam.egg-info/top_level.txt
wteamrlt/__init__.py
wteamrlt/main.py
wteamrlt.egg-info/SOURCES.txt
wteamrlt.egg-info/dependency_links.txt
wteamrlt.egg-info/top_level.txt